CHANGELOG.md
MANIFEST.in
Pipfile
Pipfile.lock
README.md
setup.py
gen3rbac.egg-info/PKG-INFO
gen3rbac.egg-info/SOURCES.txt
gen3rbac.egg-info/dependency_links.txt
gen3rbac.egg-info/requires.txt
gen3rbac.egg-info/top_level.txt
rbac/__init__.py
rbac/client/__init__.py
rbac/client/base.py
rbac/client/errors.py
rbac/client/arborist/__init__.py
rbac/client/arborist/client.py
rbac/client/arborist/errors.py