Metadata-Version: 1.0
Name: gen3rbac
Version: 0.1.2
Summary: Gen3 RBAC Client
Home-page: https://github.com/uc-cdis/rbac-client
Author: UNKNOWN
Author-email: UNKNOWN
License: Apache
Platform: UNKNOWN
